{
  "deterministic_run_id": "355814f8ccf5c3fb32ca",
  "drivers": [
    {
      "driver_share": 52.6,
      "expected_finish": 4.715333,
      "name": "RUS",
      "podium_probability": 0.823667,
      "team": "Mercedes",
      "team_share": 47.4,
      "weekend_form_delta": 4.666667,
      "win_probability": 0.457276
    },
    {
      "driver_share": 51.9,
      "expected_finish": 5.626833,
      "name": "NOR",
      "podium_probability": 0.738833,
      "team": "McLaren",
      "team_share": 48.1,
      "weekend_form_delta": 3.333333,
      "win_probability": 0.274166
    },
    {
      "driver_share": 55.0,
      "expected_finish": 6.2845,
      "name": "VER",
      "podium_probability": 0.628833,
      "team": "Red Bull Racing",
      "team_share": 45.0,
      "weekend_form_delta": 2.666667,
      "win_probability": 0.149794
    },
    {
      "driver_share": 49.8,
      "expected_finish": 6.093667,
      "name": "LEC",
      "podium_probability": 0.526167,
      "team": "Ferrari",
      "team_share": 50.2,
      "weekend_form_delta": 4.0,
      "win_probability": 0.099674
    },
    {
      "driver_share": 44.2,
      "expected_finish": 8.213333,
      "name": "HAM",
      "podium_probability": 0.106667,
      "team": "Ferrari",
      "team_share": 55.8,
      "weekend_form_delta": 4.333333,
      "win_probability": 0.006383
    },
    {
      "driver_share": 41.0,
      "expected_finish": 9.217667,
      "name": "PIA",
      "podium_probability": 0.053,
      "team": "McLaren",
      "team_share": 59.0,
      "weekend_form_delta": 3.666667,
      "win_probability": 0.005483
    },
    {
      "driver_share": 38.7,
      "expected_finish": 9.604167,
      "name": "ANT",
      "podium_probability": 0.033,
      "team": "Mercedes",
      "team_share": 61.3,
      "weekend_form_delta": 5.0,
      "win_probability": 0.002555
    },
    {
      "driver_share": 53.5,
      "expected_finish": 10.512833,
      "name": "BEA",
      "podium_probability": 0.034167,
      "team": "Haas F1 Team",
      "team_share": 46.5,
      "weekend_form_delta": 2.0,
      "win_probability": 0.001823
    },
    {
      "driver_share": 57.5,
      "expected_finish": 11.3755,
      "name": "GAS",
      "podium_probability": 0.025833,
      "team": "Alpine",
      "team_share": 42.5,
      "weekend_form_delta": 3.0,
      "win_probability": 0.001823
    },
    {
      "driver_share": 53.1,
      "expected_finish": 11.188167,
      "name": "LIN",
      "podium_probability": 0.020333,
      "team": "Racing Bulls",
      "team_share": 46.9,
      "weekend_form_delta": -0.666667,
      "win_probability": 0.001023
    },
    {
      "driver_share": 52.3,
      "expected_finish": 12.630167,
      "name": "ALB",
      "podium_probability": 0.005667,
      "team": "Williams",
      "team_share": 47.7,
      "weekend_form_delta": -2.666667,
      "win_probability": 0.0
    },
    {
      "driver_share": 37.9,
      "expected_finish": 13.563,
      "name": "HAD",
      "podium_probability": 0.000667,
      "team": "Red Bull Racing",
      "team_share": 62.1,
      "weekend_form_delta": 2.333333,
      "win_probability": 0.0
    },
    {
      "driver_share": 47.4,
      "expected_finish": 13.811333,
      "name": "OCO",
      "podium_probability": 0.001,
      "team": "Haas F1 Team",
      "team_share": 52.6,
      "weekend_form_delta": 0.0,
      "win_probability": 0.0
    },
    {
      "driver_share": 54.3,
      "expected_finish": 13.841333,
      "name": "ALO",
      "podium_probability": 0.001,
      "team": "Aston Martin",
      "team_share": 45.7,
      "weekend_form_delta": -3.0,
      "win_probability": 0.0
    },
    {
      "driver_share": 46.5,
      "expected_finish": 15.247167,
      "name": "SAI",
      "podium_probability": 0.000333,
      "team": "Williams",
      "team_share": 53.5,
      "weekend_form_delta": -2.333333,
      "win_probability": 0.0
    },
    {
      "driver_share": 53.0,
      "expected_finish": 15.371,
      "name": "BOR",
      "podium_probability": 0.0005,
      "team": "Audi",
      "team_share": 47.0,
      "weekend_form_delta": -1.0,
      "win_probability": 0.0
    },
    {
      "driver_share": 56.7,
      "expected_finish": 16.044667,
      "name": "PER",
      "podium_probability": 0.000167,
      "team": "Cadillac",
      "team_share": 43.3,
      "weekend_form_delta": -4.0,
      "win_probability": 0.0
    },
    {
      "driver_share": 48.6,
      "expected_finish": 16.090833,
      "name": "COL",
      "podium_probability": 0.0,
      "team": "Alpine",
      "team_share": 51.4,
      "weekend_form_delta": 0.333333,
      "win_probability": 0.0
    },
    {
      "driver_share": 41.1,
      "expected_finish": 16.428,
      "name": "LAW",
      "podium_probability": 0.0,
      "team": "Racing Bulls",
      "team_share": 58.9,
      "weekend_form_delta": -0.333333,
      "win_probability": 0.0
    },
    {
      "driver_share": 47.4,
      "expected_finish": 16.914,
      "name": "STR",
      "podium_probability": 0.0,
      "team": "Aston Martin",
      "team_share": 52.6,
      "weekend_form_delta": -3.666667,
      "win_probability": 0.0
    },
    {
      "driver_share": 47.9,
      "expected_finish": 17.032333,
      "name": "HUL",
      "podium_probability": 0.000167,
      "team": "Audi",
      "team_share": 52.1,
      "weekend_form_delta": 0.666667,
      "win_probability": 0.0
    },
    {
      "driver_share": 42.5,
      "expected_finish": 18.994833,
      "name": "BOT",
      "podium_probability": 0.0,
      "team": "Cadillac",
      "team_share": 57.5,
      "weekend_form_delta": -3.333333,
      "win_probability": 0.0
    }
  ],
  "generated_at": "2026-03-14T17:30:31Z",
  "inputs_used": [
    {
      "source": "qualifying",
      "source_key": "Q",
      "weight": 0.5
    },
    {
      "source": "history_driver",
      "source_key": "history_driver",
      "weight": 0.285714
    },
    {
      "source": "history_team",
      "source_key": "history_team",
      "weight": 0.214286
    }
  ],
  "integrity": {
    "driver_ratings_hash": "36c12880c500",
    "race_config_hash": "e806d5d65551",
    "team_ratings_hash": "173696d0dc30"
  },
  "prediction_target": "race",
  "prediction_target_label": "Race",
  "race": "Chinese Grand Prix",
  "season_blend": {
    "current_season": 2026,
    "current_weight": 20,
    "previous_season": 2025,
    "previous_weight": 80,
    "summary": "20% Season 2026 / 80% Season 2025"
  },
  "simulation": {
    "available_sessions": [
      "FP1",
      "SQ",
      "S",
      "Q"
    ],
    "grid_source": "qualifying",
    "overtaking_difficulty": 0.5,
    "safety_car_probability": 0.23,
    "seed": 202602,
    "simulations": 6000,
    "weather": "dry",
    "win_temperature": 1.2
  },
  "target_output_type": "race",
  "target_session_code": "R",
  "weekend_format": "sprint"
}
