{
  "data_freshness": {
    "days_since_latest_event": 0,
    "days_until_next_race": 7,
    "is_stale": false,
    "latest_completed_date": "2026-06-07",
    "latest_completed_event": "Monaco Grand Prix",
    "next_race_date": "2026-06-14",
    "reference_date": "2026-06-07",
    "stale_threshold_days": 21.0
  },
  "deterministic_run_id": "c90fb6010979c55ac291",
  "drivers": [
    {
      "driver_share": 50.4,
      "expected_position": 2.037833,
      "front_row_probability": 0.801167,
      "name": "CRA",
      "pole_probability": 0.656833,
      "team": "Aston Martin",
      "team_share": 49.6,
      "top10_probability": 0.983333,
      "weekend_form_delta": 0.0
    },
    {
      "driver_share": 46.2,
      "expected_position": 12.35,
      "front_row_probability": 0.056833,
      "name": "BOR",
      "pole_probability": 0.018,
      "team": "Audi",
      "team_share": 53.8,
      "top10_probability": 0.4205,
      "weekend_form_delta": 0.0
    },
    {
      "driver_share": 46.2,
      "expected_position": 12.427667,
      "front_row_probability": 0.052333,
      "name": "ANT",
      "pole_probability": 0.018,
      "team": "Mercedes",
      "team_share": 53.8,
      "top10_probability": 0.418833,
      "weekend_form_delta": 0.0
    },
    {
      "driver_share": 46.2,
      "expected_position": 12.689,
      "front_row_probability": 0.052833,
      "name": "RUS",
      "pole_probability": 0.017,
      "team": "Mercedes",
      "team_share": 53.8,
      "top10_probability": 0.389,
      "weekend_form_delta": 0.0
    },
    {
      "driver_share": 46.2,
      "expected_position": 12.386,
      "front_row_probability": 0.057667,
      "name": "HAD",
      "pole_probability": 0.016667,
      "team": "Red Bull Racing",
      "team_share": 53.8,
      "top10_probability": 0.412333,
      "weekend_form_delta": 0.0
    },
    {
      "driver_share": 46.2,
      "expected_position": 12.444167,
      "front_row_probability": 0.055833,
      "name": "HUL",
      "pole_probability": 0.016333,
      "team": "Audi",
      "team_share": 53.8,
      "top10_probability": 0.411167,
      "weekend_form_delta": 0.0
    },
    {
      "driver_share": 46.2,
      "expected_position": 12.437333,
      "front_row_probability": 0.056167,
      "name": "HAM",
      "pole_probability": 0.016167,
      "team": "Ferrari",
      "team_share": 53.8,
      "top10_probability": 0.404,
      "weekend_form_delta": 0.0
    },
    {
      "driver_share": 46.2,
      "expected_position": 12.575333,
      "front_row_probability": 0.0545,
      "name": "GAS",
      "pole_probability": 0.016167,
      "team": "Alpine",
      "team_share": 53.8,
      "top10_probability": 0.3985,
      "weekend_form_delta": 0.0
    },
    {
      "driver_share": 46.2,
      "expected_position": 12.389,
      "front_row_probability": 0.057333,
      "name": "NOR",
      "pole_probability": 0.015833,
      "team": "McLaren",
      "team_share": 53.8,
      "top10_probability": 0.412333,
      "weekend_form_delta": 0.0
    },
    {
      "driver_share": 46.2,
      "expected_position": 12.462333,
      "front_row_probability": 0.053167,
      "name": "LEC",
      "pole_probability": 0.015833,
      "team": "Ferrari",
      "team_share": 53.8,
      "top10_probability": 0.409833,
      "weekend_form_delta": 0.0
    },
    {
      "driver_share": 46.2,
      "expected_position": 12.558833,
      "front_row_probability": 0.0535,
      "name": "BEA",
      "pole_probability": 0.015833,
      "team": "Haas F1 Team",
      "team_share": 53.8,
      "top10_probability": 0.4045,
      "weekend_form_delta": 0.0
    },
    {
      "driver_share": 46.2,
      "expected_position": 12.459333,
      "front_row_probability": 0.055667,
      "name": "BOT",
      "pole_probability": 0.0155,
      "team": "Cadillac",
      "team_share": 53.8,
      "top10_probability": 0.413667,
      "weekend_form_delta": 0.0
    },
    {
      "driver_share": 46.2,
      "expected_position": 12.389667,
      "front_row_probability": 0.052833,
      "name": "ALO",
      "pole_probability": 0.015333,
      "team": "Aston Martin",
      "team_share": 53.8,
      "top10_probability": 0.415333,
      "weekend_form_delta": 0.0
    },
    {
      "driver_share": 46.2,
      "expected_position": 12.4095,
      "front_row_probability": 0.051167,
      "name": "LIN",
      "pole_probability": 0.015167,
      "team": "Racing Bulls",
      "team_share": 53.8,
      "top10_probability": 0.404833,
      "weekend_form_delta": 0.0
    },
    {
      "driver_share": 46.2,
      "expected_position": 12.477167,
      "front_row_probability": 0.055,
      "name": "OCO",
      "pole_probability": 0.015167,
      "team": "Haas F1 Team",
      "team_share": 53.8,
      "top10_probability": 0.409333,
      "weekend_form_delta": 0.0
    },
    {
      "driver_share": 46.2,
      "expected_position": 12.381333,
      "front_row_probability": 0.054833,
      "name": "ALB",
      "pole_probability": 0.014833,
      "team": "Williams",
      "team_share": 53.8,
      "top10_probability": 0.419167,
      "weekend_form_delta": 0.0
    },
    {
      "driver_share": 46.2,
      "expected_position": 12.429167,
      "front_row_probability": 0.053833,
      "name": "PIA",
      "pole_probability": 0.014833,
      "team": "McLaren",
      "team_share": 53.8,
      "top10_probability": 0.4135,
      "weekend_form_delta": 0.0
    },
    {
      "driver_share": 46.2,
      "expected_position": 12.338167,
      "front_row_probability": 0.0525,
      "name": "STR",
      "pole_probability": 0.014667,
      "team": "Aston Martin",
      "team_share": 53.8,
      "top10_probability": 0.419,
      "weekend_form_delta": 0.0
    },
    {
      "driver_share": 46.2,
      "expected_position": 12.379667,
      "front_row_probability": 0.051833,
      "name": "SAI",
      "pole_probability": 0.014667,
      "team": "Williams",
      "team_share": 53.8,
      "top10_probability": 0.415,
      "weekend_form_delta": 0.0
    },
    {
      "driver_share": 46.2,
      "expected_position": 12.470167,
      "front_row_probability": 0.055667,
      "name": "PER",
      "pole_probability": 0.014667,
      "team": "Cadillac",
      "team_share": 53.8,
      "top10_probability": 0.402167,
      "weekend_form_delta": 0.0
    },
    {
      "driver_share": 46.2,
      "expected_position": 12.4505,
      "front_row_probability": 0.055667,
      "name": "VER",
      "pole_probability": 0.0145,
      "team": "Red Bull Racing",
      "team_share": 53.8,
      "top10_probability": 0.413667,
      "weekend_form_delta": 0.0
    },
    {
      "driver_share": 46.2,
      "expected_position": 12.429167,
      "front_row_probability": 0.054167,
      "name": "COL",
      "pole_probability": 0.014333,
      "team": "Alpine",
      "team_share": 53.8,
      "top10_probability": 0.4115,
      "weekend_form_delta": 0.0
    },
    {
      "driver_share": 46.2,
      "expected_position": 12.628667,
      "front_row_probability": 0.0555,
      "name": "LAW",
      "pole_probability": 0.013667,
      "team": "Racing Bulls",
      "team_share": 53.8,
      "top10_probability": 0.3985,
      "weekend_form_delta": 0.0
    }
  ],
  "generated_at": "2026-06-07T17:22:46Z",
  "inputs_used": [
    {
      "source": "history_driver",
      "source_key": "history_driver",
      "weight": 0.666667
    },
    {
      "source": "history_team",
      "source_key": "history_team",
      "weight": 0.333333
    }
  ],
  "integrity": {
    "driver_ratings_hash": "e5288149e00c",
    "race_config_hash": "6313c5979da5",
    "team_ratings_hash": "b130a70a2e2f"
  },
  "prediction_target": "qualifying",
  "prediction_target_label": "Qualifying",
  "race": "Barcelona Grand Prix",
  "season_blend": {
    "current_season": 2026,
    "current_weight": 100,
    "previous_season": 2025,
    "previous_weight": 0,
    "summary": "100% Season 2026"
  },
  "simulation": {
    "available_sessions": [],
    "grid_source": "simulation",
    "qualifying_noise": 2.25,
    "seed": 202607,
    "simulations": 6000,
    "weather": "dry"
  },
  "target_output_type": "qualifying",
  "target_session_code": "Q",
  "weekend_format": "standard"
}
